CRAFT/__init__.py
CRAFT/craft_utils.py
CRAFT/predict.py
craftmoduleore-0.0.1.dist-info/METADATA
craftmoduleore-0.0.1.dist-info/WHEEL
craftmoduleore-0.0.1.dist-info/top_level.txt
craftmoduleore-0.0.1.dist-info/RECORD
