Metadata-Version: 2.1
Name: craftmoduleore
Version: 0.0.1
Summary: Craft_module
Home-page: UNKNOWN
Author: Ashok Raja
Author-email: A.Palaniswamy@gmail.com
License: UNKNOWN
Keywords: python,video,stream,video stream,camera stream,sockets
Platform: UNKNOWN
Classifier: Development Status :: 1 - Planning
Classifier: Intended Audience :: Developers
Classifier: Programming Language :: Python :: 3.8
Classifier: Operating System :: Unix
Classifier: Operating System :: MacOS :: MacOS X
Classifier: Operating System :: Microsoft :: Windows
